pyrun_injected/__init__.py
pyrun_injected/_win32utils.py
pyrun_injected/dll.cp310-win_amd64.pyd
pyrun_injected/dllinject.py
pyrun_injected/pyrun_injected.c
pyrun_injected-0.2.0.dist-info/licenses/LICENSE
pyrun_injected-0.2.0.dist-info/METADATA
pyrun_injected-0.2.0.dist-info/WHEEL
pyrun_injected-0.2.0.dist-info/top_level.txt
pyrun_injected-0.2.0.dist-info/RECORD
