Metadata-Version: 2.4
Name: pyrun_injected
Version: 0.2.0
Summary: python injector and script runner
Author: monkeyman192
Maintainer: monkeyman192
License-Expression: MIT
Requires-Python: >=3.9
License-File: LICENSE
Requires-Dist: pymem
Dynamic: license-file
